datalayer_run/__init__.py
datalayer_run/__main__.py
datalayer_run/_version.py
datalayer_run/application.py
datalayer_run/application_base.py
datalayer_run/main.py
datalayer_run/serverapplication.py
datalayer_run/app/__init__.py
datalayer_run/app/operator_app.py
datalayer_run/handlers/__init__.py
datalayer_run/handlers/base.py
datalayer_run/handlers/config/__init__.py
datalayer_run/handlers/config/handler.py
datalayer_run/handlers/echo/__init__.py
datalayer_run/handlers/echo/handler.py
datalayer_run/handlers/index/__init__.py
datalayer_run/handlers/index/handler.py
datalayer_run/handlers/ping/__init__.py
datalayer_run/handlers/ping/handler.py
datalayer_run/handlers/proxy/__init__.py
datalayer_run/handlers/proxy/handler.py
datalayer_run/handlers/relay/__init__.py
datalayer_run/handlers/relay/handler.py
datalayer_run/services/__init__.py
datalayer_run/services/kubernetes_service.py
datalayer_run/static/102.datalayer-operator.js
datalayer_run/static/1020.datalayer-operator.js
datalayer_run/static/1050.datalayer-operator.js
datalayer_run/static/1110.datalayer-operator.js
datalayer_run/static/1146.datalayer-operator.js
datalayer_run/static/1292.datalayer-operator.js
datalayer_run/static/1450.datalayer-operator.js
datalayer_run/static/1626.datalayer-operator.js
datalayer_run/static/1629.datalayer-operator.js
datalayer_run/static/1696.datalayer-operator.js
datalayer_run/static/1810.datalayer-operator.js
datalayer_run/static/1900.datalayer-operator.js
datalayer_run/static/1919.datalayer-operator.js
datalayer_run/static/1956.datalayer-operator.js
datalayer_run/static/2.datalayer-operator.js
datalayer_run/static/2003.datalayer-operator.js
datalayer_run/static/2030.datalayer-operator.js
datalayer_run/static/2066.datalayer-operator.js
datalayer_run/static/2074.datalayer-operator.js
datalayer_run/static/2086.datalayer-operator.js
datalayer_run/static/2148.datalayer-operator.js
datalayer_run/static/2218.datalayer-operator.js
datalayer_run/static/2322.datalayer-operator.js
datalayer_run-0.1.2.dist-info/METADATA
datalayer_run-0.1.2.dist-info/WHEEL
datalayer_run-0.1.2.dist-info/entry_points.txt
datalayer_run-0.1.2.dist-info/licenses/LICENSE
datalayer_run-0.1.2.dist-info/RECORD
