Metadata-Version: 2.1
Name: datalayer_run
Version: 0.1.2
Summary: Ξ 🏃 Datalayer Run.
Project-URL: Homepage, https://github.com/datalayer/datalayer-operator
Project-URL: Bug Tracker, https://github.com/datalayer/datalayer-operator/issues
Project-URL: Repository, https://github.com/datalayer/datalayer-operator.git
Author-email: Datalayer <info@datalayer.io>
License: BSD 3-Clause License
License-File: LICENSE
Classifier: Framework :: Jupyter
Classifier: Framework :: Jupyter :: JupyterLab
Classifier: Framework :: Jupyter :: JupyterLab :: 4
Classifier: Framework :: Jupyter :: JupyterLab :: Extensions
Classifier: Framework :: Jupyter :: JupyterLab :: Extensions :: Prebuilt
Classifier: Intended Audience :: Developers
Classifier: Intended Audience :: Science/Research
Classifier: Intended Audience :: System Administrators
Classifier: License :: OSI Approved :: BSD License
Classifier: Programming Language :: Python
Classifier: Programming Language :: Python :: 3
Classifier: Programming Language :: Python :: 3.9
Classifier: Programming Language :: Python :: 3.10
Classifier: Programming Language :: Python :: 3.11
Requires-Python: >=3.9
Requires-Dist: datalayer-dao
Requires-Dist: datalayer-iam
Requires-Dist: flask-cors
Requires-Dist: flask-jwt-extended==4.5.2
Requires-Dist: flask-oidc==1.4.0
Requires-Dist: flask==2.3.2
Requires-Dist: jupyter-server<3,>=2
Requires-Dist: jupyterpool
Requires-Dist: kubernetes
Requires-Dist: pillow
Provides-Extra: test
Requires-Dist: coverage; extra == 'test'
Requires-Dist: pytest; extra == 'test'
Requires-Dist: pytest-asyncio; extra == 'test'
Requires-Dist: pytest-cov; extra == 'test'
Requires-Dist: pytest-jupyter; extra == 'test'
Requires-Dist: pytest-tornasync; extra == 'test'
